odoo9_addon_openeducat_parent-9.0.2.4.0-py2.7-nspkg.pth
odoo_addons/openeducat_parent/__openerp__.py
odoo_addons/openeducat_parent/__init__.py
odoo_addons/openeducat_parent/parent_menu.xml
odoo_addons/openeducat_parent/security/op_parent_security.xml
odoo_addons/openeducat_parent/security/ir.model.access.csv
odoo_addons/openeducat_parent/models/parent.py
odoo_addons/openeducat_parent/models/__init__.py
odoo_addons/openeducat_parent/i18n/openeducat_parent.pot
odoo_addons/openeducat_parent/views/parent_view.xml
odoo_addons/openeducat_parent/demo/op.parent.csv
odoo_addons/openeducat_parent/demo/res.groups.csv
odoo_addons/openeducat_parent/demo/res.partner.csv
odoo_addons/openeducat_parent/demo/res.users.csv
odoo_addons/openeducat_parent/static/description/openeducat_logo.png
odoo_addons/openeducat_parent/static/description/openeducat_parent_banner.jpg
odoo_addons/openeducat_parent/static/description/index.html
odoo_addons/openeducat_parent/static/description/parent.png
odoo_addons/openeducat_parent/static/description/icon.png
odoo9_addon_openeducat_parent-9.0.2.4.0.dist-info/top_level.txt
odoo9_addon_openeducat_parent-9.0.2.4.0.dist-info/WHEEL
odoo9_addon_openeducat_parent-9.0.2.4.0.dist-info/RECORD
odoo9_addon_openeducat_parent-9.0.2.4.0.dist-info/metadata.json
odoo9_addon_openeducat_parent-9.0.2.4.0.dist-info/DESCRIPTION.rst
odoo9_addon_openeducat_parent-9.0.2.4.0.dist-info/METADATA
odoo9_addon_openeducat_parent-9.0.2.4.0.dist-info/namespace_packages.txt
